consoleassistant/__init__.py
consoleassistant/src/__init__.py
consoleassistant/src/main.py
consoleassistant/src/ContactManager/__init__.py
consoleassistant/src/ContactManager/contact_manager.py
consoleassistant/src/ContactManager/models.py
consoleassistant/src/EventManager/__init__.py
consoleassistant/src/EventManager/event_manager.py
consoleassistant/src/FileManager/__init__.py
consoleassistant/src/FileManager/file_sorter.py
consoleassistant/src/NoteManger/__init__.py
consoleassistant/src/NoteManger/note_manager.py
consoleassistant/src/View/__init__.py
consoleassistant/src/View/base_view.py
consoleassistant/src/tools/__init__.py
consoleassistant/src/tools/common.py
Console_Assistant_0.1_by_dreamcode-0.4.dist-info/METADATA
Console_Assistant_0.1_by_dreamcode-0.4.dist-info/WHEEL
Console_Assistant_0.1_by_dreamcode-0.4.dist-info/entry_points.txt
Console_Assistant_0.1_by_dreamcode-0.4.dist-info/top_level.txt
Console_Assistant_0.1_by_dreamcode-0.4.dist-info/RECORD
